WinTmp/LibreHardwareMonitorLib.dll
WinTmp/__init__.py
WinTmp/_version.py
wintmp-1.3.0.dist-info/licenses/LICENSE
wintmp-1.3.0.dist-info/METADATA
wintmp-1.3.0.dist-info/WHEEL
wintmp-1.3.0.dist-info/top_level.txt
wintmp-1.3.0.dist-info/RECORD
