Metadata-Version: 2.4
Name: WinTmp
Version: 1.3.0
Summary: A package used to get temperature on Windows Machines.
Author-email: Kethan Vegunta <kethan@vegunta.com>
Keywords: windows,temperature,cpu,gpu,amd,intel,nvidia
Classifier: Programming Language :: Python :: 3
Classifier: License :: OSI Approved :: MIT License
Classifier: Operating System :: Microsoft :: Windows
Requires-Python: >=3.6
License-File: LICENSE
Requires-Dist: pythonnet
Requires-Dist: wmi
Dynamic: license-file
